{"ToyLayers":[{"PlayPointLayers":[{"Points":[{"HideToyLayers":[],"PointName":"Point_1","Cats":[]}],"LayerName":"PlayPointLayer_1"}],"LayerName":"ToyLayer_stop"},{"PlayPointLayers":[{"Points":[{"HideToyLayers":["ToyLayer_stop"],"PointName":"Point_1","Cats":[{"CatName":"catani016","Animations":[{"ShadowX":"114.600","ShadowY":"30.600","RotationZ":"0.000","X":"117.700","Y":"25.200","ScaleX":"1.000","ScaleY":"1.000","ShadowScaleX":"2.000","ShadowScaleY":"2.000","AnimationName":"action0001","ShadowName":"pang2_0001yz"},{"ShadowX":"118.100","ShadowY":"50.900","RotationZ":"0.000","X":"130.200","Y":"44.800","ScaleX":"1.000","ScaleY":"1.000","ShadowScaleX":"2.000","ShadowScaleY":"2.000","AnimationName":"action1051","ShadowName":"pang2_1051yz"},{"ShadowX":"131.600","ShadowY":"39.600","RotationZ":"0.000","X":"144.500","Y":"32.200","ScaleX":"1.000","ScaleY":"1.000","ShadowScaleX":"2.000","ShadowScaleY":"2.000","AnimationName":"action1052","ShadowName":"pang2_1051yz"}]},{"CatName":"catani018","Animations":[{"ShadowX":"-102.000","ShadowY":"42.100","RotationZ":"0.000","X":"-100.600","Y":"35.500","ScaleX":"-1.000","ScaleY":"1.000","ShadowScaleX":"-2.000","ShadowScaleY":"2.000","AnimationName":"action0001","ShadowName":"pang2_0001yz"},{"ShadowX":"-113.300","ShadowY":"39.100","RotationZ":"0.000","X":"-108.800","Y":"31.900","ScaleX":"-1.000","ScaleY":"1.000","ShadowScaleX":"-2.000","ShadowScaleY":"2.000","AnimationName":"action0004","ShadowName":"pang2_0001yz"},{"ShadowX":"-128.300","ShadowY":"45.700","RotationZ":"0.000","X":"-137.200","Y":"37.900","ScaleX":"-1.000","ScaleY":"1.000","ShadowScaleX":"-2.000","ShadowScaleY":"2.000","AnimationName":"action1052","ShadowName":"pang2_1051yz"}]},{"CatName":"catani019","Animations":[{"ShadowX":"115.500","ShadowY":"40.700","RotationZ":"0.000","X":"128.800","Y":"42.900","ScaleX":"1.000","ScaleY":"1.000","ShadowScaleX":"2.000","ShadowScaleY":"2.000","AnimationName":"action0051","ShadowName":"shou_0051yz"},{"ShadowX":"126.000","ShadowY":"36.200","RotationZ":"0.000","X":"133.800","Y":"37.900","ScaleX":"1.000","ScaleY":"1.000","ShadowScaleX":"2.000","ShadowScaleY":"2.000","AnimationName":"action0053","ShadowName":"shou_0051yz"},{"ShadowX":"-113.300","ShadowY":"25.400","RotationZ":"0.000","X":"-121.600","Y":"27.000","ScaleX":"-1.000","ScaleY":"1.000","ShadowScaleX":"-2.000","ShadowScaleY":"2.000","AnimationName":"action1003","ShadowName":"shou_0051yz"}]},{"CatName":"catani009","Animations":[{"ShadowX":"-151.400","ShadowY":"24.700","RotationZ":"0.000","X":"-164.100","Y":"41.500","ScaleX":"1.000","ScaleY":"1.000","ShadowScaleX":"2.000","ShadowScaleY":"2.000","AnimationName":"action1051","ShadowName":"pang1_1051yz"}]},{"CatName":"catani023","Animations":[{"ShadowX":"147.900","ShadowY":"24.000","RotationZ":"0.000","X":"161.400","Y":"41.200","ScaleX":"-1.000","ScaleY":"1.000","ShadowScaleX":"-2.000","ShadowScaleY":"2.000","AnimationName":"action1051","ShadowName":"pang1_1051yz"}]},{"CatName":"catani025","Animations":[{"ShadowX":"136.000","ShadowY":"-3.900","RotationZ":"0.000","X":"145.500","Y":"-7.100","ScaleX":"1.000","ScaleY":"1.000","ShadowScaleX":"2.000","ShadowScaleY":"2.000","AnimationName":"action0004","ShadowName":"biaozhun_0001yz"},{"ShadowX":"148.100","ShadowY":"-3.900","RotationZ":"0.000","X":"158.300","Y":"-2.000","ScaleX":"1.000","ScaleY":"1.000","ShadowScaleX":"2.000","ShadowScaleY":"2.000","AnimationName":"action1002","ShadowName":"biaozhun_1001yz"},{"ShadowX":"-109.100","ShadowY":"11.900","RotationZ":"0.000","X":"-94.300","Y":"13.200","ScaleX":"1.000","ScaleY":"1.000","ShadowScaleX":"2.000","ShadowScaleY":"2.000","AnimationName":"action1003","ShadowName":"biaozhun_1001yz"}]}]}],"LayerName":"PlayPointLayer_1"},{"Points":[{"HideToyLayers":["ToyLayer_stop"],"PointName":"Point_1","Cats":[{"CatName":"catani016","Animations":[{"ShadowX":"152.500","ShadowY":"-42.200","RotationZ":"0.000","X":"153.700","Y":"-60.500","ScaleX":"1.000","ScaleY":"1.000","ShadowScaleX":"2.000","ShadowScaleY":"2.000","AnimationName":"action2351","ShadowName":"pang1_2351yz"},{"ShadowX":"116.500","ShadowY":"-56.700","RotationZ":"0.000","X":"131.900","Y":"-79.200","ScaleX":"1.000","ScaleY":"1.000","ShadowScaleX":"2.000","ShadowScaleY":"2.000","AnimationName":"action2151","ShadowName":"pang2_2151yz"},{"ShadowX":"47.300","ShadowY":"-69.900","RotationZ":"0.000","X":"69.100","Y":"-85.200","ScaleX":"1.000","ScaleY":"1.000","ShadowScaleX":"2.000","ShadowScaleY":"2.000","AnimationName":"action2051","ShadowName":"pang2_2051yz"}]},{"CatName":"catani018","Animations":[{"ShadowX":"-64.800","ShadowY":"-36.800","RotationZ":"0.000","X":"-87.600","Y":"-51.200","ScaleX":"-1.000","ScaleY":"1.000","ShadowScaleX":"-2.000","ShadowScaleY":"2.000","AnimationName":"action2051","ShadowName":"pang2_2051yz"},{"ShadowX":"-97.600","ShadowY":"-52.100","RotationZ":"0.000","X":"-98.100","Y":"-72.500","ScaleX":"-1.000","ScaleY":"1.000","ShadowScaleX":"-2.000","ShadowScaleY":"2.000","AnimationName":"action2151","ShadowName":"pang2_2151yz"},{"ShadowX":"145.000","ShadowY":"-52.100","RotationZ":"0.000","X":"145.900","Y":"-67.400","ScaleX":"1.000","ScaleY":"1.000","ShadowScaleX":"2.000","ShadowScaleY":"2.000","AnimationName":"action2351","ShadowName":"pang2_2351yz"}]},{"CatName":"catani019","Animations":[{"ShadowX":"130.600","ShadowY":"-7.200","RotationZ":"0.000","X":"141.600","Y":"-4.500","ScaleX":"1.000","ScaleY":"1.000","ShadowScaleX":"2.000","ShadowScaleY":"2.000","AnimationName":"action0051","ShadowName":"shou_0051yz"},{"ShadowX":"141.900","ShadowY":"-2.700","RotationZ":"0.000","X":"149.600","Y":"-2.500","ScaleX":"1.000","ScaleY":"1.000","ShadowScaleX":"2.000","ShadowScaleY":"2.000","AnimationName":"action1003","ShadowName":"shou_0051yz"}]},{"CatName":"catani009","Animations":[{"ShadowX":"141.100","ShadowY":"-44.400","RotationZ":"0.000","X":"116.100","Y":"-48.700","ScaleX":"1.000","ScaleY":"1.000","ShadowScaleX":"2.000","ShadowScaleY":"2.000","AnimationName":"action2001","ShadowName":"pang1_2001yz"},{"ShadowX":"-95.300","ShadowY":"-44.500","RotationZ":"0.000","X":"-106.600","Y":"-34.300","ScaleX":"-1.000","ScaleY":"1.000","ShadowScaleX":"-2.000","ShadowScaleY":"2.000","AnimationName":"action2101","ShadowName":"pang1_2101yz"}]},{"CatName":"catani023","Animations":[{"ShadowX":"-130.100","ShadowY":"-35.000","RotationZ":"0.000","X":"-108.600","Y":"-41.200","ScaleX":"-1.000","ScaleY":"1.000","ShadowScaleX":"-2.000","ShadowScaleY":"2.000","AnimationName":"action2001","ShadowName":"pang1_2001yz"},{"ShadowX":"-105.500","ShadowY":"-41.500","RotationZ":"0.000","X":"-113.600","Y":"-27.000","ScaleX":"-1.000","ScaleY":"1.000","ShadowScaleX":"-2.000","ShadowScaleY":"2.000","AnimationName":"action2101","ShadowName":"pang1_2101yz"},{"ShadowX":"-136.400","ShadowY":"-44.500","RotationZ":"0.000","X":"-118.200","Y":"-36.900","ScaleX":"-1.000","ScaleY":"1.000","ShadowScaleX":"-2.000","ShadowScaleY":"2.000","AnimationName":"action2351","ShadowName":"pang1_2101yz"}]},{"CatName":"catani025","Animations":[{"ShadowX":"-17.900","ShadowY":"-55.700","RotationZ":"0.000","X":"-15.700","Y":"-66.100","ScaleX":"1.000","ScaleY":"1.000","ShadowScaleX":"2.000","ShadowScaleY":"2.000","AnimationName":"action2151","ShadowName":"biaozhun_2151yz"},{"ShadowX":"65.500","ShadowY":"-40.300","RotationZ":"0.000","X":"84.500","Y":"-48.700","ScaleX":"1.000","ScaleY":"1.000","ShadowScaleX":"2.000","ShadowScaleY":"2.000","AnimationName":"action2101","ShadowName":"biaozhun_2101yz"}]}]}],"LayerName":"PlayPointLayer_2"}],"LayerName":"ToyLayer_1"}]}
