{"skeleton":{"hash":"Fl5zTZ4rNe+vNhyfH0xHi1Lej5U","spine":"2.1.27","width":1706,"height":494,"images":"./images/"},"bones":[{"name":"root"},{"name":"below","parent":"root","length":60,"rotation":270,"color":"0400ffff"},{"name":"bone104","parent":"below","x":-1108.02,"y":1018.69,"color":"00ff04ff"},{"name":"bone106","parent":"below","x":-1103.47,"y":1021.58,"color":"0400ffff"},{"name":"bone87","parent":"below","length":30,"x":-1078.53,"y":853.09,"rotation":-180,"color":"0400ffff"},{"name":"bone95","parent":"below","x":-1103.47,"y":1021.58,"color":"0400ffff"},{"name":"bone96","parent":"below","x":-1108.02,"y":1018.69,"color":"00ff04ff"},{"name":"bone105","parent":"bone104","x":19.5,"y":1.26,"color":"771effff"},{"name":"bone107","parent":"bone106","x":21,"y":42.76,"color":"771effff"},{"name":"bone97","parent":"bone95","x":21,"y":42.76,"color":"771effff"},{"name":"bone98","parent":"bone96","x":19.5,"y":1.26,"color":"771effff"}],"slots":[{"name":"yuanjing0","bone":"below","attachment":"yuanjing0"},{"name":"yingzi2","bone":"bone97","attachment":"yingzi2"},{"name":"yingzi3","bone":"bone107","attachment":"yingzi2"},{"name":"yingzi 1","bone":"bone98","attachment":"yingzi 1"},{"name":"yingzi 2","bone":"bone105","attachment":"yingzi 1"},{"name":"yuan_yyun1","bone":"bone96","attachment":"yuan_yyun1"},{"name":"yuan_yyun2","bone":"bone104","attachment":"yuan_yyun1"},{"name":"yuan_ychengbao","bone":"bone87","attachment":"yuan_ychengbao"},{"name":"yyuan_yun2","bone":"bone95","attachment":"yyuan_yun2"},{"name":"yyuan_yun3","bone":"bone106","attachment":"yyuan_yun2"}],"skins":{"default":{"yingzi 1":{"yingzi 1":{"x":9.51,"y":-5.95,"rotation":90,"width":142,"height":54}},"yingzi 2":{"yingzi 1":{"x":9.51,"y":-5.95,"rotation":90,"width":142,"height":54}},"yingzi2":{"yingzi2":{"x":0.96,"y":-10.34,"rotation":90,"width":178,"height":65}},"yingzi3":{"yingzi2":{"x":0.96,"y":-10.34,"rotation":90,"width":178,"height":65}},"yuan_ychengbao":{"yuan_ychengbao":{"x":30.96,"y":3.59,"rotation":-90,"width":75,"height":87}},"yuan_yyun1":{"yuan_yyun1":{"x":0.52,"y":-1.69,"rotation":90,"width":134,"height":87}},"yuan_yyun2":{"yuan_yyun1":{"x":0.52,"y":-1.69,"rotation":90,"width":134,"height":87}},"yuanjing0":{"yuanjing0":{"x":-930,"y":853,"rotation":90,"width":1706,"height":494}},"yyuan_yun2":{"yyuan_yun2":{"x":2.97,"y":8.41,"rotation":90,"width":188,"height":119}},"yyuan_yun3":{"yyuan_yun2":{"x":2.97,"y":8.41,"rotation":90,"width":188,"height":119}}}},"animations":{"animation":{"slots":{"yingzi2":{"color":[{"time":0,"color":"ffffff00","curve":"stepped"},{"time":0.6666,"color":"ffffff00"},{"time":2.6666,"color":"ffffffff","curve":"stepped"},{"time":20,"color":"ffffffff"}]},"yingzi3":{"color":[{"time":0,"color":"ffffffff","curve":"stepped"},{"time":20,"color":"ffffffff"}]},"yingzi 2":{"color":[{"time":0,"color":"ffffff00","curve":"stepped"},{"time":1.6666,"color":"ffffff00"},{"time":5,"color":"ffffffff","curve":"stepped"},{"time":20,"color":"ffffffff"}]},"yuan_yyun2":{"color":[{"time":0,"color":"ffffff00"},{"time":1.6666,"color":"ffffffff","curve":"stepped"},{"time":20,"color":"ffffffff"}]},"yyuan_yun2":{"color":[{"time":0,"color":"ffffff00"},{"time":1,"color":"ffffffff","curve":"stepped"},{"time":20,"color":"ffffffff"}]},"yyuan_yun3":{"color":[{"time":0,"color":"ffffffff","curve":"stepped"},{"time":20,"color":"ffffffff"}]}},"bones":{"root":{"rotate":[{"time":0,"angle":0}],"translate":[{"time":0,"x":0,"y":0}],"scale":[{"time":0,"x":1,"y":1}]},"below":{"rotate":[{"time":0,"angle":0}],"translate":[{"time":0,"x":0,"y":0}],"scale":[{"time":0,"x":1,"y":1}]},"bone87":{"rotate":[{"time":0,"angle":0}],"translate":[{"time":0,"x":0,"y":0}],"scale":[{"time":0,"x":1,"y":1}]},"bone96":{"rotate":[{"time":0,"angle":0,"curve":"stepped"},{"time":20,"angle":0}],"translate":[{"time":0,"x":0,"y":40},{"time":20,"x":0,"y":240}],"scale":[{"time":0,"x":1,"y":1,"curve":"stepped"},{"time":20,"x":1,"y":1}]},"bone97":{"rotate":[{"time":0,"angle":0,"curve":"stepped"},{"time":20,"angle":0}],"translate":[{"time":0,"x":10,"y":0},{"time":20,"x":0,"y":0}],"scale":[{"time":0,"x":1,"y":1,"curve":"stepped"},{"time":20,"x":1,"y":1}]},"bone98":{"rotate":[{"time":0,"angle":0}],"translate":[{"time":0,"x":0,"y":0}],"scale":[{"time":0,"x":1,"y":1}]},"bone95":{"rotate":[{"time":0,"angle":0,"curve":"stepped"},{"time":20,"angle":0}],"translate":[{"time":0,"x":30,"y":-310},{"time":20,"x":10,"y":-50}],"scale":[{"time":0,"x":1,"y":1,"curve":"stepped"},{"time":20,"x":1,"y":1}]},"bone106":{"rotate":[{"time":0,"angle":0,"curve":"stepped"},{"time":20,"angle":0}],"translate":[{"time":0,"x":10,"y":-50},{"time":20,"x":0,"y":310}],"scale":[{"time":0,"x":1,"y":1,"curve":"stepped"},{"time":20,"x":1,"y":1}]},"bone104":{"rotate":[{"time":0,"angle":0,"curve":"stepped"},{"time":20,"angle":0}],"translate":[{"time":0,"x":0,"y":-160},{"time":20,"x":0,"y":39.99}],"scale":[{"time":0,"x":1,"y":1,"curve":"stepped"},{"time":20,"x":1,"y":1}]},"bone107":{"rotate":[{"time":0,"angle":0,"curve":"stepped"},{"time":20,"angle":0}],"translate":[{"time":0,"x":0,"y":0,"curve":"stepped"},{"time":20,"x":0,"y":0}],"scale":[{"time":0,"x":1,"y":1,"curve":"stepped"},{"time":20,"x":1,"y":1}]}}}}}